berry/__init__.py
berry/_version.py
berry/basisrotation.py
berry/berry_geometry.py
berry/cli.py
berry/clustering_bands.py
berry/conductivity.py
berry/dotproduct.py
berry/generatewfc.py
berry/preprocessing.py
berry/r2k.py
berry/shg.py
berry/_subroutines/clustering_libs.py
berry/_subroutines/clustering_signaling.py
berry/_subroutines/comutator.py
berry/_subroutines/contatempo.py
berry/_subroutines/headerfooter.py
berry/_subroutines/loaddata.py
berry/_subroutines/loadmeta.py
berry/_subroutines/parserQE.py
berry/_subroutines/write_k_points.py
berry/utils/_logger.py
berry/utils/emailSender.py
berry/utils/jit.py
berry/vis/_debug.py
berry/vis/_geometry.py
berry/vis/_wave.py
berry_suite-1.0.2.dist-info/LICENSE.txt
berry_suite-1.0.2.dist-info/METADATA
berry_suite-1.0.2.dist-info/WHEEL
berry_suite-1.0.2.dist-info/entry_points.txt
berry_suite-1.0.2.dist-info/top_level.txt
berry_suite-1.0.2.dist-info/RECORD
