Metadata-Version: 2.1
Name: berry-suite
Version: 1.0.2
Summary: The berry suite of programs extracts the Bloch wavefunctions from DFT calculations in an ordered way so they can be directly used to make calculations.
Home-page: https://ricardoribeiro-2020.github.io/berry/
Author: Berry Developers
Author-email: ricardo.ribeiro@physics.org
License: MIT
Platform: UNKNOWN
Classifier: Programming Language :: Python :: 3.8
Classifier: Programming Language :: Python :: 3.9
Classifier: Programming Language :: Python :: 3.10
Classifier: Programming Language :: Python :: 3 :: Only
Classifier: Topic :: Scientific/Engineering :: Physics
Classifier: License :: OSI Approved :: MIT License
Classifier: Operating System :: POSIX :: Linux
License-File: LICENSE.txt
Requires-Dist: argcomplete
Requires-Dist: colorama
Requires-Dist: findiff
Requires-Dist: matplotlib
Requires-Dist: networkx
Requires-Dist: numpy
Requires-Dist: scipy
Provides-Extra: dev
Requires-Dist: twine ; extra == 'dev'
